LICENSE
MANIFEST.in
README.md
requirements.txt
setup.cfg
setup.py
onnx2keras/__init__.py
onnx2keras/activation_layers.py
onnx2keras/constant_layers.py
onnx2keras/converter.py
onnx2keras/convolution_layers.py
onnx2keras/elementwise_layers.py
onnx2keras/layers.py
onnx2keras/linear_layers.py
onnx2keras/main.py
onnx2keras/normalization_layers.py
onnx2keras/operation_layers.py
onnx2keras/padding_layers.py
onnx2keras/pooling_layers.py
onnx2keras/reshape_layers.py
onnx2keras/upsampling_layers.py
onnx2keras/utils.py
onnx2keras_tl_fork.egg-info/PKG-INFO
onnx2keras_tl_fork.egg-info/SOURCES.txt
onnx2keras_tl_fork.egg-info/dependency_links.txt
onnx2keras_tl_fork.egg-info/not-zip-safe
onnx2keras_tl_fork.egg-info/requires.txt
onnx2keras_tl_fork.egg-info/top_level.txt
test/__init__.py
test/utils.py
test/layers/__init__.py
test/layers/activations/__init__.py
test/layers/activations/test_elu.py
test/layers/activations/test_hard_tanh.py
test/layers/activations/test_leaky_relu.py
test/layers/activations/test_log_sigmoid.py
test/layers/activations/test_log_softmax.py
test/layers/activations/test_prelu.py
test/layers/activations/test_relu.py
test/layers/activations/test_relu6.py
test/layers/activations/test_selu.py
test/layers/activations/test_sigmoid.py
test/layers/activations/test_softmax.py
test/layers/activations/test_tanh.py
test/layers/activations/test_threshold.py
test/layers/constants/__init__.py
test/layers/constants/test_constant.py
test/layers/convolutions/__init__.py
test/layers/convolutions/test_conv2d.py
test/layers/convolutions/test_conv3d.py
test/layers/convolutions/test_convtranspose2d.py
test/layers/elementwise/__init__.py
test/layers/elementwise/test_add.py
test/layers/elementwise/test_div.py
test/layers/elementwise/test_mul.py
test/layers/elementwise/test_sub.py
test/layers/linears/__init__.py
test/layers/linears/test_linear.py
test/layers/normalizations/__init__.py
test/layers/normalizations/test_bn2d.py
test/layers/normalizations/test_in2d.py
test/layers/operations/__init__.py
test/layers/operations/test_cast.py
test/layers/operations/test_clip.py
test/layers/operations/test_floor.py
test/layers/operations/test_norm.py
test/layers/poolings/__init__.py
test/layers/poolings/test_avgpool2d.py
