Metadata-Version: 2.1
Name: onnx2keras-tl-fork
Version: 0.0.26
Summary: The deep learning models converter
Home-page: https://github.com/tensorleap/onnx2keras
Author: Grigory Malivenko, Doron Har Noy
Author-email: nerox8664@gmail.com, doron.harnoy@tensorleap.ai
License: MIT
Download-URL: https://github.com/tensorleap/onnx2keras/archive/v0.0.26.tar.gz
Keywords: machine-learning deep-learning pytorch keras neuralnetwork vgg resnet densenet drn dpn darknet squeezenet mobilenet onnx tensorleap
Platform: UNKNOWN
Classifier: Development Status :: 3 - Alpha
Classifier: Intended Audience :: Science/Research
Classifier: License :: OSI Approved :: MIT License
Classifier: Operating System :: OS Independent
Classifier: Programming Language :: Python
Classifier: Topic :: Scientific/Engineering :: Image Recognition
